<?xml version="1.0" encoding="UTF-8"?>
<metadata xml:lang="en"><Esri><CreaDate>20170629</CreaDate><CreaTime>09465400</CreaTime><ArcGISFormat>1.0</ArcGISFormat><SyncOnce>TRUE</SyncOnce><DataProperties><lineage><Process ToolSource="c:\program files (x86)\arcgis\desktop10.4\ArcToolbox\Toolboxes\Analysis Tools.tbx\Intersect" Date="20170629" Time="094654">Intersect "Cook_bg_wHV #;Lake_Mich_Bound #" G:\CRT\Community_Gardens\Shapefiles\Cook_bg_wHV_Intersect1.shp ALL # INPUT</Process></lineage></DataProperties></Esri></metadata>
